metacatalog_corr
