Metadata-Version: 2.1
Name: metacatalog-corr
Version: 0.1.7
Summary: Correlation metric extenstion for Metacatalog
Home-page: UNKNOWN
Author: Mirko Mälicke
Author-email: mirko.maelicke@kit.edu
License: GPL v3
Platform: UNKNOWN
